open_learning_ai_tutor/__init__.py
open_learning_ai_tutor/constants.py
open_learning_ai_tutor/intent_selector.py
open_learning_ai_tutor/intent_selector_test.py
open_learning_ai_tutor/message_tutor.py
open_learning_ai_tutor/message_tutor_test.py
open_learning_ai_tutor/prompts.py
open_learning_ai_tutor/prompts_test.py
open_learning_ai_tutor/tools.py
open_learning_ai_tutor/tutor.py
open_learning_ai_tutor/tutor_test.py
open_learning_ai_tutor/utils.py
open_learning_ai_tutor/utils_test.py
open_learning_ai_tutor-0.2.13.dist-info/METADATA
open_learning_ai_tutor-0.2.13.dist-info/WHEEL
open_learning_ai_tutor-0.2.13.dist-info/licenses/LICENSE
open_learning_ai_tutor-0.2.13.dist-info/RECORD
