Metadata-Version: 2.4
Name: open-learning-ai-tutor
Version: 0.2.13
Summary: AI powered tutor
Author: MIT ODL
License-File: LICENSE
Requires-Python: <3.14,>=3.12
Requires-Dist: e2b-code-interpreter<2,>=1.1.0
Requires-Dist: langchain-core<2.0.0,>=1.0.0
Requires-Dist: langchain-experimental<0.5,>=0.4
Requires-Dist: langchain<2.0.0,>=1.0.0
Requires-Dist: langgraph<2.0.0,>=1.0.0
Requires-Dist: langsmith<0.5.0,>=0.4.21
